dsp_bp_generator/__init__.py
dsp_bp_generator/blueprint/__init__.py
dsp_bp_generator/blueprint/blueprint.py
dsp_bp_generator/blueprint/blueprint_area.py
dsp_bp_generator/blueprint/blueprint_building.py
dsp_bp_generator/blueprint/blueprint_building_header.py
dsp_bp_generator/blueprint/blueprint_header.py
dsp_bp_generator/blueprint/blueprint_string_header.py
dsp_bp_generator/blueprint/md5.py
dsp_bp_generator/blueprint/packet.py
dsp_bp_generator/buildings/__init__.py
dsp_bp_generator/buildings/assembling_machine.py
dsp_bp_generator/buildings/building.py
dsp_bp_generator/buildings/chemical_plant.py
dsp_bp_generator/buildings/conveyer_belt.py
dsp_bp_generator/buildings/depot.py
dsp_bp_generator/buildings/lab.py
dsp_bp_generator/buildings/oil_refinary.py
dsp_bp_generator/buildings/power_distributor.py
dsp_bp_generator/buildings/smelter.py
dsp_bp_generator/buildings/sorter.py
dsp_bp_generator/buildings/splitter.py
dsp_bp_generator/enums.py
dsp_bp_generator/factory_generator/__init__.py
dsp_bp_generator/factory_generator/belt_router.py
dsp_bp_generator/factory_generator/data/recipes.yaml
dsp_bp_generator/factory_generator/factory.py
dsp_bp_generator/factory_generator/factory_block.py
dsp_bp_generator/factory_generator/factory_line.py
dsp_bp_generator/factory_generator/factory_section.py
dsp_bp_generator/factory_generator/item_flow.py
dsp_bp_generator/factory_generator/recipes.py
dsp_bp_generator/main.py
dsp_bp_generator/utils.py
dsp_bp_generator-0.1.0.dist-info/LICENSE
dsp_bp_generator-0.1.0.dist-info/METADATA
dsp_bp_generator-0.1.0.dist-info/WHEEL
dsp_bp_generator-0.1.0.dist-info/entry_points.txt
dsp_bp_generator-0.1.0.dist-info/RECORD
