Metadata-Version: 2.1
Name: dsp_bp_generator
Version: 0.1.0
Summary: This is a small project to generate blueprint to the game Dyson Sphere Program (DSP)
License: GPL-3.0-only
Author: Rasmus Stagsted
Author-email: rasmuskarnoestagsted@gmail.com
Requires-Python: >=3.11,<3.13
Classifier: License :: OSI Approved :: GNU General Public License v3 (GPLv3)
Classifier: Programming Language :: Python :: 3
Classifier: Programming Language :: Python :: 3.11
Classifier: Programming Language :: Python :: 3.12
Requires-Dist: colorama (==0.4.3)
Requires-Dist: paperclip (>=2.7.2,<3.0.0)
Requires-Dist: pyside6 (>=6.7.2,<7.0.0)
Requires-Dist: pyyaml (==5.3.1)
